repo2readme/__init__.py
repo2readme/config.py
repo2readme/cli/__init__.py
repo2readme/cli/main.py
repo2readme/loaders/__init__.py
repo2readme/loaders/loader.py
repo2readme/loaders/repo_loader.py
repo2readme/readme/__init__.py
repo2readme/readme/agent_workflow.py
repo2readme/readme/readme_generator.py
repo2readme/readme/reviewer_agent.py
repo2readme/summarize/__init__.py
repo2readme/summarize/summary.py
repo2readme/utils/__init__.py
repo2readme/utils/detect_language.py
repo2readme/utils/filter.py
repo2readme/utils/force_remove.py
repo2readme/utils/tree.py
repo2readme-1.0.2.dist-info/licenses/LICENSE
repo2readme-1.0.2.dist-info/METADATA
repo2readme-1.0.2.dist-info/WHEEL
repo2readme-1.0.2.dist-info/entry_points.txt
repo2readme-1.0.2.dist-info/top_level.txt
repo2readme-1.0.2.dist-info/RECORD
