Metadata-Version: 2.4
Name: repo2readme
Version: 1.0.2
Summary: Generate README.md from any GitHub or local repository
Author: Sarowar Jahan Biswas
License-Expression: MIT
Project-URL: Repository, https://github.com/agsaru/repo2readme
Requires-Python: >=3.10
License-File: LICENSE
Requires-Dist: click>=8.3.1
Requires-Dist: rich>=14.2.0
Requires-Dist: GitPython>=3.1.45
Requires-Dist: python-dotenv>=1.2.1
Requires-Dist: langchain>=1.2.0
Requires-Dist: langchain-community>=0.4.1
Requires-Dist: langchain-groq>=1.1.1
Requires-Dist: langchain-google-genai>=4.1.2
Requires-Dist: groq>=0.37.1
Requires-Dist: google-genai>=1.56.0
Dynamic: license-file
